castxml/_version.py
castxml/__init__.py
castxml/data/bin/castxml.exe
castxml/data/share/castxml/detect_vs.c
castxml/data/share/castxml/detect_vs.cpp
castxml/data/share/castxml/empty.c
castxml/data/share/castxml/empty.cpp
castxml/data/share/castxml/clang/include/adxintrin.h
castxml/data/share/castxml/clang/include/altivec.h
castxml/data/share/castxml/clang/include/ammintrin.h
castxml/data/share/castxml/clang/include/amxintrin.h
castxml/data/share/castxml/clang/include/arm64intr.h
castxml/data/share/castxml/clang/include/armintr.h
castxml/data/share/castxml/clang/include/arm_acle.h
castxml/data/share/castxml/clang/include/arm_bf16.h
castxml/data/share/castxml/clang/include/arm_cde.h
castxml/data/share/castxml/clang/include/arm_cmse.h
castxml/data/share/castxml/clang/include/arm_fp16.h
castxml/data/share/castxml/clang/include/arm_mve.h
castxml/data/share/castxml/clang/include/arm_neon.h
castxml/data/share/castxml/clang/include/arm_sve.h
castxml/data/share/castxml/clang/include/avx2intrin.h
castxml/data/share/castxml/clang/include/avx512bf16intrin.h
castxml/data/share/castxml/clang/include/avx512bitalgintrin.h
castxml/data/share/castxml/clang/include/avx512bwintrin.h
castxml/data/share/castxml/clang/include/avx512cdintrin.h
castxml/data/share/castxml/clang/include/avx512dqintrin.h
castxml/data/share/castxml/clang/include/avx512erintrin.h
castxml/data/share/castxml/clang/include/avx512fintrin.h
castxml/data/share/castxml/clang/include/avx512ifmaintrin.h
castxml/data/share/castxml/clang/include/avx512ifmavlintrin.h
castxml/data/share/castxml/clang/include/avx512pfintrin.h
castxml/data/share/castxml/clang/include/avx512vbmi2intrin.h
castxml/data/share/castxml/clang/include/avx512vbmiintrin.h
castxml/data/share/castxml/clang/include/avx512vbmivlintrin.h
castxml/data/share/castxml/clang/include/avx512vlbf16intrin.h
castxml/data/share/castxml/clang/include/avx512vlbitalgintrin.h
castxml/data/share/castxml/clang/include/avx512vlbwintrin.h
castxml-0.4.3.dist-info/entry_points.txt
castxml-0.4.3.dist-info/METADATA
castxml-0.4.3.dist-info/RECORD
castxml-0.4.3.dist-info/top_level.txt
castxml-0.4.3.dist-info/WHEEL
