Metadata-Version: 2.1
Name: castxml
Version: 0.4.3
Summary: Parse C-family source files and optionally write a subset of the Abstract Syntax Tree (AST) to a representation in XML.
Home-page: https://github.com/CastXML/CastXML-python-distributions#readme
Author: Kitware
Author-email: kitware@kitware.com
License: Apache 2.0
Project-URL: Bug Tracker, https://github.com/CastXML/CastXML-python-distributions/issues
Project-URL: Documentation, https://github.com/CastXML/CastXML/blob/master/doc/manual/castxml.1.rst#castxml1
Project-URL: Source Code, https://github.com/CastXML/CastXML-python-distributions
Keywords: ast xml CMake build c++ cross-platform
Platform: UNKNOWN
Classifier: License :: OSI Approved :: Apache Software License
Classifier: Programming Language :: C
Classifier: Programming Language :: C++
Classifier: Programming Language :: Python
Classifier: Operating System :: OS Independent
Classifier: Development Status :: 5 - Production/Stable
Classifier: Intended Audience :: Developers
Classifier: Topic :: Software Development :: Build Tools
